<GameTokensLibrary Name="Level" LevelName="data/Levels/DogfightModule/DFM_BrokenMoon">
 <GameToken Name="MultiplayerCheck.IsMultiplayer" Type="Bool" Value="false" LocalOnly="1"/>
 <GameToken Name="DogFightMenu.MainMenu_On" Type="Bool" Value="false" LocalOnly="1"/>
 <GameToken Name="DogFightMenu.AI_AroundPlayer_Menu" Type="Bool" Value="false" LocalOnly="1"/>
 <GameToken Name="DogFightMenu.AI_at_TeamSpawns" Type="Bool" Value="false" LocalOnly="1"/>
 <GameToken Name="Spawn_AI_at_Carriers.Spawn_Team1" Type="Bool" Value="false" LocalOnly="1"/>
 <GameToken Name="Spawn_AI_at_Carriers.Spawn_Team2" Type="Bool" Value="false" LocalOnly="1"/>
 <GameToken Name="NavMarkers.On" Type="Bool" Value="false" LocalOnly="1"/>
 <GameToken Name="Spawn_AI_Around_Player.SpawnEnemies" Type="Bool" Value="false" LocalOnly="1"/>
 <GameToken Name="PlayerPosition.Player1" Type="String" Value="0_1_1" LocalOnly="1"/>
</GameTokensLibrary>
