<ATLConfig atl_name="SC_MCCS_Airlock_Console_UI">
	<AudioTriggers>
		<ATLTrigger atl_name="Play_MCCS_Airlock_Console_UI" path="Events/">
			<WwiseEvent wwise_duration_max="1.533333" wwise_duration_min="0.527299" wwise_duration_type="OneShot" wwise_name="Play_MCCS_Airlock_Console_UI" wwise_radius_max="10.000000"/>
			<ATLPreload atl_name="SC_MCCS_Airlock_Console_UI"/>
		</ATLTrigger>
	</AudioTriggers>
	<AudioPreloads>
		<ATLPreloadRequest atl_name="SC_MCCS_Airlock_Console_UI" atl_type="AutoLoad" path="Banks/">
			<ATLPlatforms>
				<Platform atl_config_group_name="default" atl_name="pc"/>
			</ATLPlatforms>
			<ATLConfigGroup atl_name="default">
				<WwiseFile wwise_name="MCCS_Airlock_Console_UI.bnk"/>
			</ATLConfigGroup>
		</ATLPreloadRequest>
	</AudioPreloads>
</ATLConfig>
